notebooks/__init__.py
scipe/__init__.py
scipe/algorithm.py
scipe/app.py
scipe/helpers.py
scipe/llm_as_judge.py
src/__init__.py
src/algorithm.py
src/helpers.py
src/llm_as_judge.py
src/main.py
src/middleware.py
src/prompt.py
scipe-1.5.2.dist-info/METADATA
scipe-1.5.2.dist-info/WHEEL
scipe-1.5.2.dist-info/top_level.txt
scipe-1.5.2.dist-info/RECORD
