Metadata-Version: 2.1
Name: scipe
Version: 1.5.2
Summary: Systematic Chain Improvement and Problem Evaluation
Home-page: 
Author: Ankush Garg
Author-email: ankush-garg@berkeley.edu
Requires-Python: >=3.9
Requires-Dist: langchain-core ==0.2.28
Requires-Dist: langgraph ==0.1.19
Requires-Dist: ipykernel ==5.5.6
Requires-Dist: pandas ==2.2.2
Requires-Dist: python-dotenv ==1.0.1
Requires-Dist: openpyxl ==3.1.5
Requires-Dist: litellm ==1.46.5
